sodas_sdk/__init__.py
sodas_sdk/py.typed
sodas_sdk/core/__init__.py
sodas_sdk/core/error.py
sodas_sdk/core/functionality_error.py
sodas_sdk/core/init.py
sodas_sdk/core/type.py
sodas_sdk/core/util.py
sodas_sdk/core/values.py
sodas_sdk/sodas_sdk_class/__init__.py
sodas_sdk/sodas_sdk_class/dcat_class.py
sodas_sdk/sodas_sdk_class/governance_class.py
sodas_sdk/sodas_sdk_class/sodas_sdk_class.py
sodas_sdk/sodas_sdk_class/DCAT/__init__.py
sodas_sdk/sodas_sdk_class/DCAT/data_service.py
sodas_sdk/sodas_sdk_class/DCAT/dataset.py
sodas_sdk/sodas_sdk_class/DCAT/dataset_series.py
sodas_sdk/sodas_sdk_class/DCAT/dcat_resource.py
sodas_sdk/sodas_sdk_class/DCAT/distribution.py
sodas_sdk/sodas_sdk_class/DCAT/version_info.py
sodas_sdk/sodas_sdk_class/PROF/__init__.py
sodas_sdk/sodas_sdk_class/PROF/options.py
sodas_sdk/sodas_sdk_class/PROF/profile.py
sodas_sdk/sodas_sdk_class/PROF/resource_descriptor.py
sodas_sdk/sodas_sdk_class/SODAS/__init__.py
sodas_sdk/sodas_sdk_class/SODAS/template.py
sodas_sdk/sodas_sdk_class/SODAS/template_artifact.py
sodas_sdk/sodas_sdk_class/SODAS/template_detail.py
sodas_sdk/sodas_sdk_class/dictionary/__init__.py
sodas_sdk/sodas_sdk_class/dictionary/term.py
sodas_sdk/sodas_sdk_class/dictionary/vocabulary.py
sodas_sdk/sodas_sdk_file/__init__.py
sodas_sdk/sodas_sdk_file/artifact_file.py
sodas_sdk/sodas_sdk_file/data_file.py
sodas_sdk/sodas_sdk_file/sodas_sdk_file.py
sodas_sdk/sodas_sdk_file/thumbnail_file.py
py_sodas_sdk-1.1.0.dist-info/METADATA
py_sodas_sdk-1.1.0.dist-info/WHEEL
py_sodas_sdk-1.1.0.dist-info/top_level.txt
py_sodas_sdk-1.1.0.dist-info/RECORD
